gradio_image_prompter/__init__.py
gradio_image_prompter/image_prompter.py
gradio_image_prompter/image_prompter.pyi
gradio_image_prompter/templates/component/__vite-browser-external-2447137e.js
gradio_image_prompter/templates/component/index.js
gradio_image_prompter/templates/component/style.css
gradio_image_prompter/templates/component/wrapper-6f348d45-f837cf34.js
gradio_image_prompter/templates/example/index.js
gradio_image_prompter/templates/example/style.css
gradio_image_prompter-0.1.0.dist-info/METADATA
gradio_image_prompter-0.1.0.dist-info/WHEEL
gradio_image_prompter-0.1.0.dist-info/licenses/LICENSE
gradio_image_prompter-0.1.0.dist-info/RECORD
